LICENSE
README.md
setup.py
src/GeoSnipe.egg-info/PKG-INFO
src/GeoSnipe.egg-info/SOURCES.txt
src/GeoSnipe.egg-info/dependency_links.txt
src/GeoSnipe.egg-info/entry_points.txt
src/GeoSnipe.egg-info/requires.txt
src/GeoSnipe.egg-info/top_level.txt
src/geosnipe/__init__.py
src/geosnipe/__main__.py
src/geosnipe/argparser.py
src/geosnipe/constants.py
src/geosnipe/functions.py
src/geosnipe/github.py
src/geosnipe/progressbar.py
src/geosnipe/ssh.py
src/geosnipe/auth/microsoft.py
src/geosnipe/auth/mojang.py