Metadata-Version: 2.1
Name: GeoSnipe
Version: 1.2.3
Summary: A pythonic Minecraft username sniper based on asyncio.
Home-page: https://github.com/Geographs/GeoSnipe
Author: Geographs
Author-email: 87452561+Geographs@users.noreply.github.com
Maintainer: Geographs
License: MIT
Download-URL: https://github.com/Geographs/GeoSnipe/releases
Project-URL: GitHub, https://github.com/Geographs/GeoSnipe
Project-URL: Documentation, https://docs.geographs.pro
Project-URL: Bug Tracker, https://github.com/Geographs/GeoSnipe/issues
Platform: UNKNOWN
Classifier: Programming Language :: Python :: 3
Classifier: License :: OSI Approved :: MIT License
Classifier: Operating System :: OS Independent
Requires-Python: >=3.9
